localStoragePro/__init__.py
localStoragePro/async_storage.py
localStoragePro/py.typed
localStoragePro/storage_backends.py
localstoragepro-0.3.0.dist-info/licenses/LICENSE
localstoragepro-0.3.0.dist-info/METADATA
localstoragepro-0.3.0.dist-info/WHEEL
localstoragepro-0.3.0.dist-info/top_level.txt
localstoragepro-0.3.0.dist-info/RECORD
