Metadata-Version: 2.4
Name: localStoragePro
Version: 0.3.0
Summary: A familiar API from the Web, adapted to storing data locally with Python.
Author-email: Suraj Mandal <localstoragepro.oss@mandalsuraj.com>
Maintainer-email: Suraj Mandal <localstoragepro.oss@mandalsuraj.com>
License-Expression: MIT
Project-URL: Homepage, https://github.com/surajmandalcell/localStoragePro
Project-URL: Bug Reports, https://github.com/surajmandalcell/localStoragePro/issues
Project-URL: Source, https://github.com/surajmandalcell/localStoragePro
Project-URL: Documentation, https://github.com/surajmandalcell/localStoragePro#readme
Keywords: localStorage,storage,database,sqlite,json,local,data
Classifier: Development Status :: 4 - Beta
Classifier: Intended Audience :: Developers
Classifier: Operating System :: OS Independent
Classifier: Programming Language :: Python :: 3
Classifier: Programming Language :: Python :: 3.9
Classifier: Programming Language :: Python :: 3.10
Classifier: Programming Language :: Python :: 3.11
Classifier: Programming Language :: Python :: 3.12
Classifier: Topic :: Software Development :: Libraries :: Python Modules
Classifier: Topic :: Database
Classifier: Topic :: System :: Archiving
Requires-Python: >=3.9
License-File: LICENSE
Provides-Extra: dev
Requires-Dist: pytest>=8.3.5; extra == "dev"
Requires-Dist: pytest-asyncio>=0.23.5; extra == "dev"
Requires-Dist: twine; extra == "dev"
Requires-Dist: build; extra == "dev"
Dynamic: license-file
